{"bins":50,"width":0.4,"dataset":[{"umaban":"01","name":"ライステラス","pdf":[{"x":62.9,"y":1.96e-05},{"x":67.77,"y":0.00273},{"x":68.18,"y":0.0114},{"x":68.59,"y":0.0367},{"x":68.99,"y":0.0962},{"x":69.4,"y":0.206},{"x":69.8,"y":0.338},{"x":70.21,"y":0.43},{"x":70.62,"y":0.444},{"x":71.02,"y":0.37},{"x":71.43,"y":0.248},{"x":71.84,"y":0.142},{"x":72.24,"y":0.074},{"x":72.65,"y":0.0354},{"x":73.05,"y":0.0155},{"x":73.46,"y":0.00647},{"x":73.87,"y":0.00254},{"x":74.27,"y":0.000931},{"x":76.3,"y":3.64e-05},{"x":82.8,"y":1.96e-05}]},{"umaban":"02","name":"アランルース","pdf":[{"x":63.54,"y":1.63e-05},{"x":68.42,"y":0.00269},{"x":68.82,"y":0.0118},{"x":69.23,"y":0.0399},{"x":69.64,"y":0.107},{"x":70.04,"y":0.23},{"x":70.45,"y":0.37},{"x":70.85,"y":0.454},{"x":71.26,"y":0.445},{"x":71.67,"y":0.351},{"x":72.07,"y":0.223},{"x":72.48,"y":0.12},{"x":72.88,"y":0.059},{"x":73.29,"y":0.0269},{"x":73.7,"y":0.0114},{"x":74.1,"y":0.00466},{"x":74.51,"y":0.00181},{"x":75.32,"y":0.00027},{"x":83.44,"y":1.63e-05}]},{"umaban":"03","name":"ニシノステディー","pdf":[{"x":63.7,"y":9.28e-06},{"x":68.17,"y":0.00111},{"x":68.57,"y":0.00578},{"x":68.98,"y":0.0241},{"x":69.39,"y":0.0751},{"x":69.79,"y":0.179},{"x":70.2,"y":0.334},{"x":70.6,"y":0.46},{"x":71.01,"y":0.472},{"x":71.42,"y":0.388},{"x":71.82,"y":0.262},{"x":72.23,"y":0.144},{"x":72.63,"y":0.0674},{"x":73.04,"y":0.029},{"x":73.45,"y":0.0119},{"x":73.85,"y":0.00471},{"x":74.26,"y":0.00185},{"x":75.07,"y":0.000275},{"x":83.6,"y":9.28e-06}]},{"umaban":"04","name":"メイショウエデン","pdf":[{"x":63.32,"y":1.13e-05},{"x":68.2,"y":0.00207},{"x":68.6,"y":0.00937},{"x":69.01,"y":0.0324},{"x":69.41,"y":0.0906},{"x":69.82,"y":0.203},{"x":70.23,"y":0.343},{"x":70.63,"y":0.444},{"x":71.04,"y":0.459},{"x":71.44,"y":0.377},{"x":71.85,"y":0.247},{"x":72.26,"y":0.136},{"x":72.66,"y":0.0673},{"x":73.07,"y":0.0306},{"x":73.48,"y":0.0126},{"x":73.88,"y":0.00497},{"x":74.29,"y":0.00184},{"x":75.1,"y":0.000229},{"x":83.22,"y":1.13e-05}]},{"umaban":"05","name":"セイバリー","pdf":[{"x":63.67,"y":1.26e-05},{"x":68.54,"y":0.0024},{"x":68.95,"y":0.011},{"x":69.35,"y":0.0386},{"x":69.76,"y":0.107},{"x":70.16,"y":0.233},{"x":70.57,"y":0.379},{"x":70.98,"y":0.464},{"x":71.38,"y":0.451},{"x":71.79,"y":0.35},{"x":72.19,"y":0.217},{"x":72.6,"y":0.114},{"x":73.01,"y":0.0544},{"x":73.41,"y":0.0241},{"x":73.82,"y":0.00988},{"x":74.22,"y":0.00393},{"x":74.63,"y":0.00149},{"x":75.44,"y":0.000214},{"x":83.57,"y":1.26e-05}]},{"umaban":"06","name":"デルマドゥルガー","pdf":[{"x":63.55,"y":2.2e-05},{"x":68.42,"y":0.00435},{"x":68.83,"y":0.0179},{"x":69.24,"y":0.0569},{"x":69.64,"y":0.142},{"x":70.05,"y":0.278},{"x":70.45,"y":0.411},{"x":70.86,"y":0.462},{"x":71.27,"y":0.417},{"x":71.67,"y":0.307},{"x":72.08,"y":0.185},{"x":72.48,"y":0.0961},{"x":72.89,"y":0.046},{"x":73.3,"y":0.0209},{"x":73.7,"y":0.00903},{"x":74.11,"y":0.00384},{"x":74.52,"y":0.00158},{"x":75.33,"y":0.000289},{"x":83.45,"y":2.2e-05}]},{"umaban":"07","name":"レナキックス","pdf":[{"x":63.82,"y":3.27e-05},{"x":68.69,"y":0.00391},{"x":69.1,"y":0.0155},{"x":69.5,"y":0.0479},{"x":69.91,"y":0.119},{"x":70.32,"y":0.239},{"x":70.72,"y":0.369},{"x":71.13,"y":0.44},{"x":71.53,"y":0.426},{"x":71.94,"y":0.337},{"x":72.35,"y":0.219},{"x":72.75,"y":0.123},{"x":73.16,"y":0.0639},{"x":73.57,"y":0.031},{"x":73.97,"y":0.0141},{"x":74.38,"y":0.00623},{"x":74.78,"y":0.00262},{"x":75.19,"y":0.00107},{"x":77.22,"y":6.05e-05},{"x":83.72,"y":3.27e-05}]},{"umaban":"08","name":"ラグランダム","pdf":[{"x":63.48,"y":3.26e-05},{"x":68.36,"y":0.00396},{"x":68.76,"y":0.0157},{"x":69.17,"y":0.049},{"x":69.58,"y":0.122},{"x":69.98,"y":0.244},{"x":70.39,"y":0.374},{"x":70.79,"y":0.443},{"x":71.2,"y":0.425},{"x":71.61,"y":0.333},{"x":72.01,"y":0.215},{"x":72.42,"y":0.12},{"x":72.82,"y":0.0615},{"x":73.23,"y":0.0297},{"x":73.64,"y":0.0135},{"x":74.04,"y":0.00595},{"x":74.45,"y":0.00251},{"x":74.86,"y":0.00103},{"x":76.89,"y":6.03e-05},{"x":83.38,"y":3.26e-05}]},{"umaban":"09","name":"マハリクマハリタ","pdf":[{"x":64.63,"y":1.29e-05},{"x":69.1,"y":0.0012},{"x":69.5,"y":0.00601},{"x":69.91,"y":0.0248},{"x":70.32,"y":0.077},{"x":70.72,"y":0.183},{"x":71.13,"y":0.338},{"x":71.53,"y":0.462},{"x":71.94,"y":0.471},{"x":72.35,"y":0.383},{"x":72.75,"y":0.257},{"x":73.16,"y":0.142},{"x":73.56,"y":0.0666},{"x":73.97,"y":0.029},{"x":74.38,"y":0.0122},{"x":74.78,"y":0.00495},{"x":75.19,"y":0.00201},{"x":76,"y":0.000329},{"x":84.53,"y":1.29e-05}]},{"umaban":"10","name":"コスモラングデン","pdf":[{"x":63.86,"y":2.35e-05},{"x":68.33,"y":0.00137},{"x":68.73,"y":0.00621},{"x":69.14,"y":0.0243},{"x":69.55,"y":0.0732},{"x":69.95,"y":0.171},{"x":70.36,"y":0.315},{"x":70.76,"y":0.437},{"x":71.17,"y":0.46},{"x":71.58,"y":0.391},{"x":71.98,"y":0.275},{"x":72.39,"y":0.159},{"x":72.8,"y":0.0802},{"x":73.2,"y":0.0376},{"x":73.61,"y":0.0169},{"x":74.01,"y":0.00733},{"x":74.42,"y":0.00316},{"x":74.83,"y":0.00134},{"x":76.04,"y":0.000157},{"x":83.76,"y":2.35e-05}]},{"umaban":"11","name":"メイビーサムタイム","pdf":[{"x":64.48,"y":1.98e-05},{"x":69.35,"y":0.00475},{"x":69.76,"y":0.0198},{"x":70.16,"y":0.063},{"x":70.57,"y":0.156},{"x":70.97,"y":0.3},{"x":71.38,"y":0.433},{"x":71.79,"y":0.469},{"x":72.19,"y":0.407},{"x":72.6,"y":0.288},{"x":73.01,"y":0.168},{"x":73.41,"y":0.0838},{"x":73.82,"y":0.0388},{"x":74.22,"y":0.0171},{"x":74.63,"y":0.00728},{"x":75.04,"y":0.00307},{"x":75.44,"y":0.00126},{"x":76.66,"y":0.000137},{"x":84.38,"y":1.98e-05}]},{"umaban":"12","name":"マイネルスフィア","pdf":[{"x":63.84,"y":1.77e-05},{"x":68.71,"y":0.00299},{"x":69.12,"y":0.0132},{"x":69.53,"y":0.045},{"x":69.93,"y":0.12},{"x":70.34,"y":0.252},{"x":70.74,"y":0.395},{"x":71.15,"y":0.466},{"x":71.56,"y":0.438},{"x":71.96,"y":0.331},{"x":72.37,"y":0.203},{"x":72.77,"y":0.106},{"x":73.18,"y":0.0505},{"x":73.59,"y":0.0227},{"x":73.99,"y":0.00958},{"x":74.4,"y":0.00396},{"x":74.8,"y":0.00157},{"x":75.62,"y":0.00026},{"x":83.74,"y":1.77e-05}]},{"umaban":"13","name":"コスモサンドリヨン","pdf":[{"x":63.56,"y":1.38e-05},{"x":68.43,"y":0.00246},{"x":68.84,"y":0.0111},{"x":69.24,"y":0.0381},{"x":69.65,"y":0.104},{"x":70.06,"y":0.227},{"x":70.46,"y":0.369},{"x":70.87,"y":0.457},{"x":71.27,"y":0.45},{"x":71.68,"y":0.355},{"x":72.09,"y":0.224},{"x":72.49,"y":0.12},{"x":72.9,"y":0.0584},{"x":73.3,"y":0.0263},{"x":73.71,"y":0.0109},{"x":74.12,"y":0.00439},{"x":74.52,"y":0.00168},{"x":75.34,"y":0.000239},{"x":83.46,"y":1.38e-05}]},{"umaban":"14","name":"トウカイギアー","pdf":[{"x":63.68,"y":2.87e-05},{"x":68.55,"y":0.00457},{"x":68.96,"y":0.0184},{"x":69.37,"y":0.0578},{"x":69.77,"y":0.142},{"x":70.18,"y":0.277},{"x":70.58,"y":0.408},{"x":70.99,"y":0.458},{"x":71.4,"y":0.414},{"x":71.8,"y":0.306},{"x":72.21,"y":0.186},{"x":72.61,"y":0.0982},{"x":73.02,"y":0.048},{"x":73.43,"y":0.0223},{"x":73.83,"y":0.00989},{"x":74.24,"y":0.00432},{"x":74.65,"y":0.00183},{"x":75.46,"y":0.000358},{"x":83.58,"y":2.87e-05}]}]}
